README.md
setup.py
lco_ingester/__init__.py
lco_ingester/archive.py
lco_ingester/exceptions.py
lco_ingester/fits.py
lco_ingester/ingester.py
lco_ingester/postproc.py
lco_ingester/s3.py
lco_ingester.egg-info/PKG-INFO
lco_ingester.egg-info/SOURCES.txt
lco_ingester.egg-info/dependency_links.txt
lco_ingester.egg-info/entry_points.txt
lco_ingester.egg-info/requires.txt
lco_ingester.egg-info/top_level.txt
lco_ingester/scripts/__init__.py
lco_ingester/scripts/ingest_frame.py
lco_ingester/settings/__init__.py
lco_ingester/settings/celery_config.py
lco_ingester/settings/log_config.py
lco_ingester/settings/settings.py
lco_ingester/utils/__init__.py
lco_ingester/utils/fits.py
lco_ingester/utils/metrics.py