Metadata-Version: 2.1
Name: lco-ingester
Version: 2.1.15
Summary: Ingest frames into the LCO Archive
Home-page: https://github.com/LCOGT/ingester
License: UNKNOWN
Platform: UNKNOWN
Classifier: License :: OSI Approved :: GNU General Public License v3 (GPLv3)
Requires-Python: >=3.5
